{"ref": "org.freedesktop.Platform.GL.nvidia-470-74/1.4", "stats": [{"date": "2021/09/22", "arches": {"i386": [5, 0], "x86_64": [1681, 8]}}, {"date": "2021/09/23", "arches": {"i386": [5, 0], "x86_64": [1209, 5]}}, {"date": "2021/09/24", "arches": {"i386": [2, 0], "x86_64": [1025, 4]}}, {"date": "2021/09/25", "arches": {"i386": [1, 0], "x86_64": [890, 4]}}, {"date": "2021/09/26", "arches": {"i386": [5, 4], "x86_64": [1176, 43]}}, {"date": "2021/09/27", "arches": {"i386": [12, 8], "x86_64": [1478, 62]}}, {"date": "2021/09/28", "arches": {"i386": [12, 5], "x86_64": [1410, 42]}}, {"date": "2021/09/29", "arches": {"i386": [5, 4], "x86_64": [1928, 32]}}, {"date": "2021/09/30", "arches": {"i386": [8, 1], "x86_64": [2302, 21]}}, {"date": "2021/10/01", "arches": {"i386": [2, 1], "x86_64": [1723, 25]}}, {"date": "2021/10/02", "arches": {"i386": [9, 1], "x86_64": [1575, 16]}}, {"date": "2021/10/03", "arches": {"i386": [2, 0], "x86_64": [1333, 10]}}, {"date": "2021/10/04", "arches": {"i386": [8, 0], "x86_64": [1344, 16]}}, {"date": "2021/10/05", "arches": {"x86_64": [1479, 16]}}, {"date": "2021/10/06", "arches": {"i386": [4, 0], "x86_64": [1188, 13]}}, {"date": "2021/10/07", "arches": {"i386": [1, 0], "x86_64": [1053, 22]}}, {"date": "2021/10/08", "arches": {"i386": [3, 2], "x86_64": [6943, 5948]}}, {"date": "2021/10/09", "arches": {"x86_64": [3442, 2497]}}, {"date": "2021/10/10", "arches": {"i386": [2, 2], "x86_64": [2070, 1114]}}, {"date": "2021/10/11", "arches": {"i386": [2, 1], "x86_64": [2038, 1021]}}, {"date": "2021/10/12", "arches": {"i386": [1, 0], "x86_64": [1594, 595]}}, {"date": "2021/10/13", "arches": {"i386": [1, 0], "x86_64": [1497, 479]}}, {"date": "2021/10/14", "arches": {"i386": [2, 0], "x86_64": [1383, 318]}}, {"date": "2021/10/15", "arches": {"i386": [2, 0], "x86_64": [9328, 7789]}}, {"date": "2021/10/16", "arches": {"i386": [8, 0], "x86_64": [3476, 2011]}}, {"date": "2021/10/17", "arches": {"i386": [3, 0], "x86_64": [2282, 967]}}, {"date": "2021/10/18", "arches": {"x86_64": [2152, 944]}}, {"date": "2021/10/19", "arches": {"i386": [3, 0], "x86_64": [1814, 521]}}, {"date": "2021/10/20", "arches": {"i386": [6, 5], "x86_64": [2884, 490]}}, {"date": "2021/10/21", "arches": {"i386": [15, 6], "x86_64": [3798, 451]}}, {"date": "2021/10/22", "arches": {"i386": [10, 5], "x86_64": [3423, 372]}}, {"date": "2021/10/23", "arches": {"i386": [17, 14], "x86_64": [4781, 1833]}}, {"date": "2021/10/24", "arches": {"i386": [48, 44], "x86_64": [12889, 10309]}}, {"date": "2021/10/25", "arches": {"i386": [21, 18], "x86_64": [7197, 4692]}}, {"date": "2021/10/26", "arches": {"i386": [17, 11], "x86_64": [5805, 3381]}}, {"date": "2021/10/27", "arches": {"i386": [57, 55], "x86_64": [15878, 13625]}}, {"date": "2021/10/28", "arches": {"i386": [9, 9], "x86_64": [5846, 3664]}}, {"date": "2021/10/29", "arches": {"i386": [10, 8], "x86_64": [4076, 2010]}}, {"date": "2021/10/30", "arches": {"i386": [11, 11], "x86_64": [3331, 1316]}}, {"date": "2021/10/31", "arches": {"i386": [2, 2], "x86_64": [2951, 1100]}}, {"date": "2021/11/01", "arches": {"i386": [6, 5], "x86_64": [3046, 1116]}}, {"date": "2021/11/02", "arches": {"i386": [5, 5], "x86_64": [2712, 862]}}, {"date": "2021/11/03", "arches": {"i386": [12, 10], "x86_64": [4215, 2506]}}, {"date": "2021/11/04", "arches": {"i386": [49, 45], "x86_64": [15792, 14243]}}, {"date": "2021/11/05", "arches": {"i386": [18, 13], "x86_64": [5452, 3974]}}, {"date": "2021/11/06", "arches": {"i386": [7, 6], "x86_64": [3654, 2261]}}, {"date": "2021/11/07", "arches": {"i386": [9, 8], "x86_64": [14348, 12856]}}, {"date": "2021/11/08", "arches": {"i386": [9, 5], "x86_64": [7839, 6540]}}, {"date": "2021/11/09", "arches": {"i386": [4, 2], "x86_64": [3707, 3005]}}, {"date": "2021/11/10", "arches": {"i386": [3, 3], "x86_64": [2400, 2010]}}, {"date": "2021/11/11", "arches": {"i386": [5, 4], "x86_64": [13513, 13206]}}, {"date": "2021/11/12", "arches": {"i386": [2, 2], "x86_64": [4764, 4437]}}, {"date": "2021/11/13", "arches": {"i386": [4, 2], "x86_64": [2285, 2010]}}, {"date": "2021/11/14", "arches": {"i386": [1, 1], "x86_64": [1778, 1548]}}, {"date": "2021/11/15", "arches": {"i386": [2, 1], "x86_64": [1747, 1469]}}, {"date": "2021/11/16", "arches": {"x86_64": [1311, 1056]}}, {"date": "2021/11/17", "arches": {"i386": [2, 1], "x86_64": [1007, 778]}}, {"date": "2021/11/18", "arches": {"i386": [3, 1], "x86_64": [838, 680]}}, {"date": "2021/11/19", "arches": {"i386": [48, 48], "x86_64": [12419, 12278]}}, {"date": "2021/11/20", "arches": {"i386": [17, 17], "x86_64": [3379, 3216]}}, {"date": "2021/11/21", "arches": {"i386": [6, 6], "x86_64": [2265, 2092]}}, {"date": "2021/11/22", "arches": {"i386": [5, 5], "x86_64": [1972, 1814]}}, {"date": "2021/11/23", "arches": {"i386": [4, 4], "x86_64": [10109, 9897]}}, {"date": "2021/11/24", "arches": {"i386": [8, 7], "x86_64": [5664, 5488]}}, {"date": "2021/11/25", "arches": {"i386": [3, 3], "x86_64": [2314, 2156]}}, {"date": "2021/11/26", "arches": {"i386": [3, 3], "x86_64": [1498, 1333]}}, {"date": "2021/11/27", "arches": {"i386": [1, 1], "x86_64": [1400, 1214]}}, {"date": "2021/11/28", "arches": {"x86_64": [1041, 919]}}, {"date": "2021/11/29", "arches": {"i386": [1, 1], "x86_64": [1202, 1058]}}, {"date": "2021/11/30", "arches": {"i386": [3, 3], "x86_64": [1026, 905]}}, {"date": "2021/12/01", "arches": {"i386": [2, 1], "x86_64": [799, 670]}}, {"date": "2021/12/02", "arches": {"i386": [1, 0], "x86_64": [696, 582]}}, {"date": "2021/12/03", "arches": {"x86_64": [601, 477]}}, {"date": "2021/12/04", "arches": {"i386": [1, 1], "x86_64": [640, 506]}}, {"date": "2021/12/05", "arches": {"i386": [3, 3], "x86_64": [475, 348]}}, {"date": "2021/12/06", "arches": {"i386": [2, 0], "x86_64": [471, 356]}}, {"date": "2021/12/07", "arches": {"i386": [2, 2], "x86_64": [430, 321]}}, {"date": "2021/12/08", "arches": {"i386": [2, 2], "x86_64": [402, 258]}}, {"date": "2021/12/09", "arches": {"i386": [3, 1], "x86_64": [376, 255]}}, {"date": "2021/12/10", "arches": {"x86_64": [364, 254]}}, {"date": "2021/12/11", "arches": {"i386": [2, 2], "x86_64": [365, 235]}}, {"date": "2021/12/12", "arches": {"i386": [1, 1], "x86_64": [332, 224]}}, {"date": "2021/12/13", "arches": {"x86_64": [380, 242]}}, {"date": "2021/12/14", "arches": {"x86_64": [274, 190]}}, {"date": "2021/12/15", "arches": {"x86_64": [10392, 10292]}}, {"date": "2021/12/16", "arches": {"i386": [3, 0], "x86_64": [3351, 3258]}}, {"date": "2021/12/17", "arches": {"i386": [1, 0], "x86_64": [1740, 1637]}}, {"date": "2021/12/18", "arches": {"x86_64": [1420, 1318]}}, {"date": "2021/12/19", "arches": {"x86_64": [8003, 7900]}}, {"date": "2021/12/20", "arches": {"x86_64": [3001, 2922]}}, {"date": "2021/12/21", "arches": {"x86_64": [1234, 1137]}}, {"date": "2021/12/22", "arches": {"x86_64": [808, 731]}}, {"date": "2021/12/23", "arches": {"x86_64": [574, 492]}}, {"date": "2021/12/24", "arches": {"x86_64": [481, 406]}}, {"date": "2021/12/25", "arches": {"x86_64": [319, 245]}}, {"date": "2021/12/26", "arches": {"x86_64": [308, 228]}}, {"date": "2021/12/27", "arches": {"x86_64": [330, 269]}}, {"date": "2021/12/28", "arches": {"i386": [1, 0], "x86_64": [316, 240]}}, {"date": "2021/12/29", "arches": {"x86_64": [606, 538]}}, {"date": "2021/12/30", "arches": {"x86_64": [8755, 8671]}}, {"date": "2021/12/31", "arches": {"x86_64": [2115, 2025]}}, {"date": "2022/01/01", "arches": {"x86_64": [1250, 1204]}}, {"date": "2022/01/02", "arches": {"x86_64": [1275, 1213]}}, {"date": "2022/01/03", "arches": {"i386": [1, 0], "x86_64": [1484, 1414]}}, {"date": "2022/01/04", "arches": {"x86_64": [1280, 1214]}}, {"date": "2022/01/05", "arches": {"x86_64": [855, 807]}}, {"date": "2022/01/06", "arches": {"x86_64": [748, 670]}}, {"date": "2022/01/07", "arches": {"i386": [1, 0], "x86_64": [634, 545]}}, {"date": "2022/01/08", "arches": {"x86_64": [518, 462]}}, {"date": "2022/01/09", "arches": {"x86_64": [417, 373]}}, {"date": "2022/01/10", "arches": {"i386": [1, 0], "x86_64": [612, 569]}}, {"date": "2022/01/11", "arches": {"i386": [3, 3], "x86_64": [846, 773]}}, {"date": "2022/01/12", "arches": {"i386": [39, 39], "x86_64": [9349, 9266]}}, {"date": "2022/01/13", "arches": {"i386": [6, 6], "x86_64": [2712, 2657]}}, {"date": "2022/01/14", "arches": {"i386": [5, 5], "x86_64": [1485, 1418]}}, {"date": "2022/01/15", "arches": {"i386": [30, 29], "x86_64": [7629, 7558]}}, {"date": "2022/01/16", "arches": {"i386": [16, 16], "x86_64": [2846, 2802]}}, {"date": "2022/01/17", "arches": {"i386": [7, 7], "x86_64": [2629, 2577]}}, {"date": "2022/01/18", "arches": {"i386": [4, 4], "x86_64": [1400, 1352]}}]}