{"ref": "org.freedesktop.Platform.GL.nvidia-460-39/1.4", "stats": [{"date": "2021/01/26", "arches": {"x86_64": [217, 9]}}, {"date": "2021/01/27", "arches": {"i386": [20, 8], "x86_64": [1969, 143]}}, {"date": "2021/01/28", "arches": {"i386": [18, 9], "x86_64": [2807, 1322]}}, {"date": "2021/01/29", "arches": {"i386": [23, 7], "x86_64": [1461, 308]}}, {"date": "2021/01/30", "arches": {"i386": [16, 5], "x86_64": [1178, 161]}}, {"date": "2021/01/31", "arches": {"i386": [10, 2], "x86_64": [949, 84]}}, {"date": "2021/02/01", "arches": {"i386": [10, 2], "x86_64": [1048, 94]}}, {"date": "2021/02/02", "arches": {"i386": [12, 1], "x86_64": [1998, 61]}}, {"date": "2021/02/03", "arches": {"i386": [31, 3], "x86_64": [4891, 76]}}, {"date": "2021/02/04", "arches": {"i386": [50, 5], "x86_64": [4306, 56]}}, {"date": "2021/02/05", "arches": {"i386": [22, 2], "x86_64": [3544, 58]}}, {"date": "2021/02/06", "arches": {"i386": [23, 3], "x86_64": [2840, 76]}}, {"date": "2021/02/07", "arches": {"i386": [11, 2], "x86_64": [2664, 51]}}, {"date": "2021/02/08", "arches": {"i386": [12, 1], "x86_64": [2775, 50]}}, {"date": "2021/02/09", "arches": {"i386": [18, 2], "x86_64": [2957, 57]}}, {"date": "2021/02/10", "arches": {"i386": [6, 1], "x86_64": [2952, 43]}}, {"date": "2021/02/11", "arches": {"i386": [13, 3], "x86_64": [2607, 53]}}, {"date": "2021/02/12", "arches": {"i386": [12, 2], "x86_64": [2377, 45]}}, {"date": "2021/02/13", "arches": {"i386": [9, 2], "x86_64": [2398, 37]}}, {"date": "2021/02/14", "arches": {"i386": [10, 1], "x86_64": [2027, 28]}}, {"date": "2021/02/15", "arches": {"i386": [6, 0], "x86_64": [2081, 38]}}, {"date": "2021/02/16", "arches": {"i386": [17, 1], "x86_64": [2074, 51]}}, {"date": "2021/02/17", "arches": {"i386": [5, 1], "x86_64": [2242, 31]}}, {"date": "2021/02/18", "arches": {"i386": [4, 0], "x86_64": [2071, 47]}}, {"date": "2021/02/19", "arches": {"i386": [6, 3], "x86_64": [16023, 14255]}}, {"date": "2021/02/20", "arches": {"i386": [9, 2], "x86_64": [6231, 4468]}}, {"date": "2021/02/21", "arches": {"i386": [7, 1], "x86_64": [4481, 2675]}}, {"date": "2021/02/22", "arches": {"i386": [4, 0], "x86_64": [4258, 2508]}}, {"date": "2021/02/23", "arches": {"i386": [10, 3], "x86_64": [3442, 1625]}}, {"date": "2021/02/24", "arches": {"i386": [47, 23], "x86_64": [7978, 1787]}}, {"date": "2021/02/25", "arches": {"i386": [54, 21], "x86_64": [8954, 1629]}}, {"date": "2021/02/26", "arches": {"i386": [40, 13], "x86_64": [26223, 21429]}}, {"date": "2021/02/27", "arches": {"i386": [23, 12], "x86_64": [9428, 5388]}}, {"date": "2021/02/28", "arches": {"i386": [38, 13], "x86_64": [6607, 3116]}}, {"date": "2021/03/01", "arches": {"i386": [22, 11], "x86_64": [6490, 3112]}}, {"date": "2021/03/02", "arches": {"i386": [16, 9], "x86_64": [4594, 1764]}}, {"date": "2021/03/03", "arches": {"i386": [11, 1], "x86_64": [4165, 1399]}}, {"date": "2021/03/04", "arches": {"i386": [9, 1], "x86_64": [3676, 1126]}}, {"date": "2021/03/05", "arches": {"i386": [21, 7], "x86_64": [3220, 945]}}, {"date": "2021/03/06", "arches": {"i386": [6, 4], "x86_64": [2759, 811]}}, {"date": "2021/03/07", "arches": {"i386": [5, 1], "x86_64": [6904, 5072]}}, {"date": "2021/03/08", "arches": {"i386": [5, 1], "x86_64": [25601, 23908]}}, {"date": "2021/03/09", "arches": {"i386": [6, 5], "x86_64": [8504, 7052]}}, {"date": "2021/03/10", "arches": {"i386": [6, 3], "x86_64": [5436, 3992]}}, {"date": "2021/03/11", "arches": {"i386": [3, 1], "x86_64": [4156, 2676]}}, {"date": "2021/03/12", "arches": {"i386": [5, 2], "x86_64": [3655, 2154]}}, {"date": "2021/03/13", "arches": {"i386": [11, 4], "x86_64": [3181, 1756]}}, {"date": "2021/03/14", "arches": {"i386": [9, 5], "x86_64": [2840, 1414]}}, {"date": "2021/03/15", "arches": {"i386": [5, 4], "x86_64": [2848, 1423]}}, {"date": "2021/03/16", "arches": {"i386": [6, 3], "x86_64": [2445, 1145]}}, {"date": "2021/03/17", "arches": {"i386": [4, 3], "x86_64": [2191, 906]}}, {"date": "2021/03/18", "arches": {"i386": [5, 3], "x86_64": [1951, 734]}}, {"date": "2021/03/19", "arches": {"i386": [4, 2], "x86_64": [1825, 657]}}, {"date": "2021/03/20", "arches": {"i386": [11, 8], "x86_64": [9383, 8322]}}, {"date": "2021/03/21", "arches": {"i386": [5, 3], "x86_64": [4041, 2927]}}, {"date": "2021/03/22", "arches": {"i386": [11, 1], "x86_64": [1694, 642]}}, {"date": "2021/03/23", "arches": {"i386": [10, 5], "x86_64": [1348, 314]}}, {"date": "2021/03/24", "arches": {"i386": [3, 1], "x86_64": [1264, 238]}}, {"date": "2021/03/25", "arches": {"i386": [5, 2], "x86_64": [1163, 207]}}, {"date": "2021/03/26", "arches": {"i386": [4, 1], "x86_64": [1104, 191]}}, {"date": "2021/03/27", "arches": {"i386": [1, 1], "x86_64": [1107, 159]}}, {"date": "2021/03/28", "arches": {"i386": [6, 2], "x86_64": [1047, 128]}}, {"date": "2021/03/29", "arches": {"i386": [5, 3], "x86_64": [1007, 121]}}, {"date": "2021/03/30", "arches": {"i386": [5, 2], "x86_64": [958, 124]}}, {"date": "2021/03/31", "arches": {"i386": [5, 1], "x86_64": [27037, 26162]}}, {"date": "2021/04/01", "arches": {"i386": [81, 77], "x86_64": [14393, 13487]}}, {"date": "2021/04/02", "arches": {"i386": [142, 142], "x86_64": [20187, 19262]}}, {"date": "2021/04/03", "arches": {"i386": [46, 44], "x86_64": [6813, 6003]}}, {"date": "2021/04/04", "arches": {"i386": [36, 35], "x86_64": [4776, 3942]}}, {"date": "2021/04/05", "arches": {"i386": [40, 39], "x86_64": [5372, 4546]}}, {"date": "2021/04/06", "arches": {"i386": [25, 24], "x86_64": [4876, 3991]}}, {"date": "2021/04/07", "arches": {"i386": [14, 14], "x86_64": [3657, 2736]}}, {"date": "2021/04/08", "arches": {"i386": [10, 9], "x86_64": [2890, 2038]}}, {"date": "2021/04/09", "arches": {"i386": [16, 13], "x86_64": [2559, 1762]}}, {"date": "2021/04/10", "arches": {"i386": [10, 9], "x86_64": [2323, 1482]}}, {"date": "2021/04/11", "arches": {"i386": [5, 5], "x86_64": [2216, 1320]}}, {"date": "2021/04/12", "arches": {"i386": [18, 17], "x86_64": [2411, 1561]}}, {"date": "2021/04/13", "arches": {"i386": [11, 11], "x86_64": [2221, 1356]}}, {"date": "2021/04/14", "arches": {"i386": [12, 12], "x86_64": [1796, 1150]}}, {"date": "2021/04/15", "arches": {"i386": [5, 5], "x86_64": [12748, 12481]}}, {"date": "2021/04/16", "arches": {"i386": [2, 2], "x86_64": [19516, 19306]}}, {"date": "2021/04/17", "arches": {"i386": [7, 6], "x86_64": [6097, 5923]}}, {"date": "2021/04/18", "arches": {"i386": [5, 5], "x86_64": [4040, 3924]}}, {"date": "2021/04/19", "arches": {"i386": [2, 2], "x86_64": [4563, 4437]}}, {"date": "2021/04/20", "arches": {"i386": [4, 4], "x86_64": [2874, 2751]}}, {"date": "2021/04/21", "arches": {"i386": [5, 5], "x86_64": [2188, 2045]}}, {"date": "2021/04/22", "arches": {"i386": [2, 2], "x86_64": [1904, 1813]}}, {"date": "2021/04/23", "arches": {"i386": [1, 1], "x86_64": [8572, 8510]}}, {"date": "2021/04/24", "arches": {"i386": [9, 9], "x86_64": [15401, 15334]}}, {"date": "2021/04/25", "arches": {"i386": [4, 4], "x86_64": [5464, 5399]}}, {"date": "2021/04/26", "arches": {"i386": [4, 4], "x86_64": [6059, 5973]}}, {"date": "2021/04/27", "arches": {"i386": [2, 2], "x86_64": [3059, 2967]}}, {"date": "2021/04/28", "arches": {"i386": [2, 2], "x86_64": [2244, 2156]}}, {"date": "2021/04/29", "arches": {"i386": [2, 2], "x86_64": [1726, 1663]}}, {"date": "2021/04/30", "arches": {"x86_64": [20818, 20748]}}, {"date": "2021/05/01", "arches": {"i386": [1, 1], "x86_64": [5151, 5070]}}, {"date": "2021/05/02", "arches": {"i386": [1, 1], "x86_64": [4919, 4842]}}, {"date": "2021/05/03", "arches": {"i386": [2, 2], "x86_64": [16471, 16396]}}, {"date": "2021/05/04", "arches": {"i386": [1, 1], "x86_64": [3936, 3879]}}, {"date": "2021/05/05", "arches": {"x86_64": [2090, 2014]}}, {"date": "2021/05/06", "arches": {"i386": [2, 2], "x86_64": [1401, 1330]}}, {"date": "2021/05/07", "arches": {"i386": [1, 0], "x86_64": [1148, 1068]}}, {"date": "2021/05/08", "arches": {"x86_64": [1040, 975]}}, {"date": "2021/05/09", "arches": {"x86_64": [768, 717]}}, {"date": "2021/05/10", "arches": {"x86_64": [698, 639]}}, {"date": "2021/05/11", "arches": {"x86_64": [657, 618]}}, {"date": "2021/05/12", "arches": {"x86_64": [552, 500]}}, {"date": "2021/05/13", "arches": {"i386": [1, 1], "x86_64": [4139, 4054]}}, {"date": "2021/05/14", "arches": {"x86_64": [5822, 5781]}}, {"date": "2021/05/15", "arches": {"i386": [2, 2], "x86_64": [3039, 2982]}}, {"date": "2021/05/16", "arches": {"i386": [2, 2], "x86_64": [2458, 2391]}}, {"date": "2021/05/17", "arches": {"x86_64": [2690, 2652]}}, {"date": "2021/05/18", "arches": {"x86_64": [1689, 1641]}}, {"date": "2021/05/19", "arches": {"i386": [3, 3], "x86_64": [18573, 18527]}}, {"date": "2021/05/20", "arches": {"i386": [1, 1], "x86_64": [14262, 14232]}}, {"date": "2021/05/21", "arches": {"x86_64": [2530, 2481]}}, {"date": "2021/05/22", "arches": {"x86_64": [1014, 972]}}, {"date": "2021/05/23", "arches": {"x86_64": [706, 666]}}, {"date": "2021/05/24", "arches": {"x86_64": [728, 683]}}, {"date": "2021/05/25", "arches": {"x86_64": [643, 603]}}, {"date": "2021/05/26", "arches": {"x86_64": [494, 441]}}, {"date": "2021/05/27", "arches": {"x86_64": [320, 291]}}, {"date": "2021/05/28", "arches": {"x86_64": [292, 256]}}, {"date": "2021/05/29", "arches": {"x86_64": [240, 207]}}, {"date": "2021/05/30", "arches": {"x86_64": [201, 174]}}, {"date": "2021/05/31", "arches": {"x86_64": [245, 214]}}, {"date": "2021/06/01", "arches": {"i386": [1, 1], "x86_64": [232, 202]}}, {"date": "2021/06/02", "arches": {"x86_64": [247, 204]}}, {"date": "2021/06/03", "arches": {"x86_64": [212, 168]}}, {"date": "2021/06/04", "arches": {"i386": [1, 1], "x86_64": [194, 151]}}, {"date": "2021/06/05", "arches": {"i386": [1, 1], "x86_64": [173, 142]}}, {"date": "2021/06/06", "arches": {"i386": [2, 2], "x86_64": [183, 150]}}, {"date": "2021/06/07", "arches": {"x86_64": [18379, 18349]}}, {"date": "2021/06/08", "arches": {"i386": [1, 1], "x86_64": [5263, 5230]}}, {"date": "2021/06/09", "arches": {"x86_64": [3378, 3351]}}, {"date": "2021/06/10", "arches": {"x86_64": [2361, 2325]}}, {"date": "2021/06/11", "arches": {"x86_64": [1807, 1779]}}, {"date": "2021/06/12", "arches": {"x86_64": [1481, 1453]}}, {"date": "2021/06/13", "arches": {"i386": [3, 3], "x86_64": [1172, 1144]}}, {"date": "2021/06/14", "arches": {"i386": [4, 4], "x86_64": [1218, 1184]}}, {"date": "2021/06/15", "arches": {"x86_64": [935, 914]}}, {"date": "2021/06/16", "arches": {"x86_64": [742, 719]}}, {"date": "2021/06/17", "arches": {"x86_64": [694, 674]}}, {"date": "2021/06/18", "arches": {"x86_64": [620, 595]}}, {"date": "2021/06/19", "arches": {"x86_64": [603, 574]}}, {"date": "2021/06/20", "arches": {"i386": [1, 1], "x86_64": [553, 527]}}, {"date": "2021/06/21", "arches": {"i386": [1, 1], "x86_64": [611, 580]}}, {"date": "2021/06/22", "arches": {"x86_64": [3153, 3140]}}, {"date": "2021/06/23", "arches": {"x86_64": [15849, 15830]}}, {"date": "2021/06/24", "arches": {"x86_64": [4421, 4406]}}, {"date": "2021/06/25", "arches": {"x86_64": [4293, 4278]}}, {"date": "2021/06/26", "arches": {"x86_64": [10569, 10551]}}, {"date": "2021/06/27", "arches": {"i386": [3, 3], "x86_64": [3121, 3108]}}, {"date": "2021/06/28", "arches": {"x86_64": [3533, 3511]}}, {"date": "2021/06/29", "arches": {"i386": [2, 2], "x86_64": [1491, 1476]}}, {"date": "2021/06/30", "arches": {"x86_64": [1091, 1073]}}, {"date": "2021/07/01", "arches": {"x86_64": [771, 747]}}, {"date": "2021/07/02", "arches": {"x86_64": [511, 502]}}, {"date": "2021/07/03", "arches": {"x86_64": [343, 323]}}, {"date": "2021/07/04", "arches": {"x86_64": [351, 322]}}, {"date": "2021/07/05", "arches": {"i386": [1, 1], "x86_64": [362, 347]}}, {"date": "2021/07/06", "arches": {"x86_64": [320, 281]}}, {"date": "2021/07/07", "arches": {"x86_64": [283, 240]}}, {"date": "2021/07/08", "arches": {"x86_64": [207, 189]}}, {"date": "2021/07/09", "arches": {"x86_64": [242, 218]}}, {"date": "2021/07/10", "arches": {"x86_64": [183, 164]}}, {"date": "2021/07/11", "arches": {"i386": [1, 1], "x86_64": [126, 119]}}, {"date": "2021/07/12", "arches": {"x86_64": [177, 162]}}, {"date": "2021/07/13", "arches": {"x86_64": [134, 125]}}, {"date": "2021/07/14", "arches": {"x86_64": [157, 145]}}, {"date": "2021/07/15", "arches": {"i386": [1, 1], "x86_64": [115, 93]}}, {"date": "2021/07/16", "arches": {"x86_64": [110, 93]}}, {"date": "2021/07/17", "arches": {"x86_64": [90, 82]}}, {"date": "2021/07/18", "arches": {"i386": [1, 1], "x86_64": [84, 67]}}, {"date": "2021/07/19", "arches": {"x86_64": [94, 81]}}, {"date": "2021/07/20", "arches": {"x86_64": [12249, 12232]}}, {"date": "2021/07/21", "arches": {"i386": [1, 1], "x86_64": [3820, 3809]}}, {"date": "2021/07/22", "arches": {"x86_64": [9727, 9712]}}, {"date": "2021/07/23", "arches": {"x86_64": [2243, 2234]}}, {"date": "2021/07/24", "arches": {"x86_64": [884, 866]}}, {"date": "2021/07/25", "arches": {"x86_64": [563, 552]}}, {"date": "2021/07/26", "arches": {"x86_64": [674, 659]}}, {"date": "2021/07/27", "arches": {"x86_64": [433, 423]}}, {"date": "2021/07/28", "arches": {"x86_64": [352, 348]}}, {"date": "2021/07/29", "arches": {"x86_64": [261, 257]}}, {"date": "2021/07/30", "arches": {"x86_64": [197, 186]}}, {"date": "2021/07/31", "arches": {"x86_64": [190, 184]}}, {"date": "2021/08/01", "arches": {"x86_64": [170, 158]}}, {"date": "2021/08/02", "arches": {"x86_64": [192, 178]}}, {"date": "2021/08/03", "arches": {"x86_64": [109, 98]}}]}