{"ref": "org.freedesktop.Platform.GL.nvidia-465-27/1.4", "stats": [{"date": "2021/04/30", "arches": {"i386": [2, 0], "x86_64": [576, 1]}}, {"date": "2021/05/01", "arches": {"x86_64": [599, 1]}}, {"date": "2021/05/02", "arches": {"i386": [4, 2], "x86_64": [621, 107]}}, {"date": "2021/05/03", "arches": {"x86_64": [975, 449]}}, {"date": "2021/05/04", "arches": {"i386": [1, 1], "x86_64": [584, 136]}}, {"date": "2021/05/05", "arches": {"i386": [2, 0], "x86_64": [437, 60]}}, {"date": "2021/05/06", "arches": {"i386": [4, 0], "x86_64": [876, 48]}}, {"date": "2021/05/07", "arches": {"i386": [8, 3], "x86_64": [1310, 46]}}, {"date": "2021/05/08", "arches": {"i386": [5, 1], "x86_64": [1224, 68]}}, {"date": "2021/05/09", "arches": {"i386": [14, 4], "x86_64": [1009, 35]}}, {"date": "2021/05/10", "arches": {"i386": [6, 0], "x86_64": [1145, 44]}}, {"date": "2021/05/11", "arches": {"i386": [7, 1], "x86_64": [964, 31]}}, {"date": "2021/05/12", "arches": {"i386": [4, 1], "x86_64": [755, 28]}}, {"date": "2021/05/13", "arches": {"i386": [5, 0], "x86_64": [1203, 545]}}, {"date": "2021/05/14", "arches": {"i386": [4, 0], "x86_64": [1601, 995]}}, {"date": "2021/05/15", "arches": {"i386": [9, 1], "x86_64": [1003, 492]}}, {"date": "2021/05/16", "arches": {"i386": [10, 2], "x86_64": [905, 340]}}, {"date": "2021/05/17", "arches": {"i386": [5, 2], "x86_64": [952, 398]}}, {"date": "2021/05/18", "arches": {"i386": [3, 0], "x86_64": [697, 212]}}, {"date": "2021/05/19", "arches": {"i386": [4, 1], "x86_64": [3764, 3309]}}, {"date": "2021/05/20", "arches": {"i386": [2, 0], "x86_64": [2571, 2206]}}, {"date": "2021/05/21", "arches": {"i386": [4, 1], "x86_64": [881, 526]}}, {"date": "2021/05/22", "arches": {"i386": [4, 0], "x86_64": [530, 175]}}, {"date": "2021/05/23", "arches": {"i386": [4, 0], "x86_64": [440, 109]}}, {"date": "2021/05/24", "arches": {"i386": [4, 1], "x86_64": [452, 107]}}, {"date": "2021/05/25", "arches": {"i386": [6, 1], "x86_64": [438, 97]}}, {"date": "2021/05/26", "arches": {"i386": [2, 0], "x86_64": [391, 50]}}, {"date": "2021/05/27", "arches": {"i386": [3, 0], "x86_64": [265, 35]}}, {"date": "2021/05/28", "arches": {"i386": [3, 0], "x86_64": [201, 18]}}, {"date": "2021/05/29", "arches": {"i386": [2, 0], "x86_64": [133, 30]}}, {"date": "2021/05/30", "arches": {"i386": [6, 0], "x86_64": [163, 19]}}]}