{"ref": "org.freedesktop.Platform.GL32.nvidia-450-119-03/1.4", "stats": [{"date": "2021/04/23", "arches": {"x86_64": [49, 0]}}, {"date": "2021/04/24", "arches": {"x86_64": [154, 0]}}, {"date": "2021/04/25", "arches": {"x86_64": [82, 0]}}, {"date": "2021/04/26", "arches": {"x86_64": [73, 0]}}, {"date": "2021/04/27", "arches": {"x86_64": [68, 0]}}, {"date": "2021/04/28", "arches": {"x86_64": [49, 2]}}, {"date": "2021/04/29", "arches": {"x86_64": [49, 1]}}, {"date": "2021/04/30", "arches": {"x86_64": [346, 296]}}, {"date": "2021/05/01", "arches": {"x86_64": [97, 56]}}, {"date": "2021/05/02", "arches": {"x86_64": [106, 77]}}, {"date": "2021/05/03", "arches": {"x86_64": [292, 273]}}, {"date": "2021/05/04", "arches": {"x86_64": [91, 55]}}, {"date": "2021/05/05", "arches": {"x86_64": [61, 27]}}, {"date": "2021/05/06", "arches": {"x86_64": [39, 15]}}, {"date": "2021/05/07", "arches": {"x86_64": [29, 12]}}, {"date": "2021/05/08", "arches": {"x86_64": [23, 10]}}, {"date": "2021/05/09", "arches": {"x86_64": [32, 8]}}, {"date": "2021/05/10", "arches": {"x86_64": [23, 3]}}, {"date": "2021/05/11", "arches": {"x86_64": [26, 8]}}, {"date": "2021/05/12", "arches": {"x86_64": [30, 8]}}, {"date": "2021/05/13", "arches": {"x86_64": [92, 69]}}]}